
{ "class": "it.csi.sigit.sigitwebn.presentation.sigitwebn.security.ComplexUISecConstraint",
  "constrainedBehavior": 2,
  "defaultState": true,
  "nomeContainer": "cpGestLibScheda6_4Dett",
  "nomeWidget": "btSalva",
  "constraints": [
{ "class": "it.csi.sigit.sigitwebn.presentation.sigitwebn.security.DeclarativeUIConstraint",
  "constrainedBehavior": 2,
  "defaultState": true,
  "nomeContainer": "cpGestLibScheda6_4Dett",
  "nomeWidget": "btSalva",
	"language": "beanshell",
	"script": "it.csi.sigit.sigitwebn.util.GenericUtil.isUtenteAutorLibWebScheda6_4(model.appDatautenteLoggato)"
}


  ]
}
