
{ "class": "it.csi.sigit.sigitwebn.presentation.sigitwebn.security.ComplexUISecConstraint",
  "constrainedBehavior": 2,
  "defaultState": true,
  "nomeContainer": "cpGestLibScheda15Dett",
  "nomeWidget": "btnEliminaDocumento",
  "constraints": [
{ "class": "it.csi.sigit.sigitwebn.presentation.sigitwebn.security.DeclarativeUIConstraint",
  "constrainedBehavior": 2,
  "defaultState": true,
  "nomeContainer": "cpGestLibScheda15Dett",
  "nomeWidget": "btnEliminaDocumento",
	"language": "beanshell",
	"script": "model.appDataelencoDocumenti != null && model.appDataelencoDocumenti.size() > 0"
}
,{ "class": "it.csi.sigit.sigitwebn.presentation.sigitwebn.security.CustomUISecConstraint",
  "constrainedBehavior": 2,
  "defaultState": true,
  "nomeContainer": "cpGestLibScheda15Dett",
  "nomeWidget": "btnEliminaDocumento",
	"methodNameSuffix": "IsAbilitatoElimDoc"
}


  ]
}
