
{ "class": "it.csi.sigit.sigitwebn.presentation.sigitwebn.security.ComplexUISecConstraint",
  "constrainedBehavior": 1,
  "defaultState": true,
  "nomeContainer": "cpDettaglioIspezione2018",
  "nomeWidget": "cbIspPagemento",
  "constraints": [
{ "class": "it.csi.sigit.sigitwebn.presentation.sigitwebn.security.DeclarativeUIConstraint",
  "constrainedBehavior": 1,
  "defaultState": true,
  "nomeContainer": "cpDettaglioIspezione2018",
  "nomeWidget": "cbIspPagemento",
	"language": "beanshell",
	"script": "it.csi.sigit.sigitwebn.business.elenco_ispezioni_impianti.CPBECpDettaglioIspezione2018.isCampoIspezioneEditabile(model)"
}


  ]
}
